simple_json_mapped_dict.py
simple_json_mapped_dict-0.1.0a0.dist-info/licenses/LICENSE
simple_json_mapped_dict-0.1.0a0.dist-info/METADATA
simple_json_mapped_dict-0.1.0a0.dist-info/WHEEL
simple_json_mapped_dict-0.1.0a0.dist-info/top_level.txt
simple_json_mapped_dict-0.1.0a0.dist-info/RECORD
