Metadata-Version: 2.4
Name: simple-json-mapped-dict
Version: 0.1.0a0
Summary: A simple `MutableMapping` (dict-like) that transparently persists its contents to a JSON file on disk. Uses only the most reliable file opening modes (`r` and `w`). Maximum compatibility with network filesystems (e.g. NAS, SSHFS, NFS), at the cost of atomicity and data race safety.
Author-email: Jifeng Wu <jifengwu2k@gmail.com>
License-Expression: MIT
Project-URL: Homepage, https://github.com/jifengwu2k/simple-json-mapped-dict
Project-URL: Bug Tracker, https://github.com/jifengwu2k/simple-json-mapped-dict/issues
Classifier: Programming Language :: Python :: 2
Classifier: Programming Language :: Python :: 3
Classifier: Operating System :: OS Independent
Requires-Python: >=2
License-File: LICENSE
Requires-Dist: typing; python_version < "3.5"
Dynamic: license-file
